natest/__init__.py
natest-0.9.dist-info/LICENSE
natest-0.9.dist-info/METADATA
natest-0.9.dist-info/WHEEL
natest-0.9.dist-info/top_level.txt
natest-0.9.dist-info/RECORD
