Metadata-Version: 2.1
Name: natest
Version: 0.9
Summary: python unit test for network automation code
Home-page: https://gitlab.com/networkAutomation/natest
Author: Federico Olivieri
Author-email: lvrfrc87@gmail.com
License: UNKNOWN
Platform: UNKNOWN
Classifier: Programming Language :: Python :: 3
Classifier: License :: OSI Approved :: MIT License
Classifier: Operating System :: OS Independent
Requires-Dist: termcolor
